spycy/__init__.py
spycy/__main__.py
spycy/dfsmatcher.py
spycy/errors.py
spycy/expression_evaluator.py
spycy/graph.py
spycy/matcher.py
spycy/pattern_graph.py
spycy/spycy.py
spycy/types.py
spycy/visitor.py
spycy/functions/__init__.py
spycy/functions/aggregation_fns.py
spycy/functions/list_fns.py
spycy/functions/logarithmic_fns.py
spycy/functions/numeric_fns.py
spycy/functions/predicate_fns.py
spycy/functions/scalar_fns.py
spycy/functions/string_fns.py
spycy/functions/trignometric_fns.py
spycy/gen/Cypher.g4
spycy/gen/Cypher.interp
spycy/gen/Cypher.tokens
spycy/gen/CypherLexer.interp
spycy/gen/CypherLexer.py
spycy/gen/CypherLexer.tokens
spycy/gen/CypherListener.py
spycy/gen/CypherParser.py
spycy/gen/grammar.cypher
spycy/gen/tck.g4
spycy_aneeshdurg-0.0.3.dist-info/METADATA
spycy_aneeshdurg-0.0.3.dist-info/WHEEL
spycy_aneeshdurg-0.0.3.dist-info/licenses/LICENSE
spycy_aneeshdurg-0.0.3.dist-info/RECORD
