Metadata-Version: 2.1
Name: spycy_aneeshdurg
Version: 0.0.3
Summary: openCypher implemented in python
Project-URL: Homepage, https://github.com/aneeshdurg/spycy
Project-URL: Bug Tracker, https://github.com/aneeshdurg/spycy/issues
Author-email: Aneesh Durg <aneeshdurg17@gmail.com>
License-File: LICENSE
Classifier: License :: OSI Approved :: MIT License
Classifier: Operating System :: OS Independent
Classifier: Programming Language :: Python :: 3
Classifier: Topic :: Database :: Database Engines/Servers
Requires-Python: >=3.10
Requires-Dist: antlr4-python3-runtime==4.12.0
Requires-Dist: networkx>=2.8.8
Requires-Dist: numpy>=1.24.2
Requires-Dist: pandas>=1.5.3
